coalex/__init__.py
coalex/approve.py
coalex/metrics.py
coalex/otel/__init__.py
coalex/otel/register.py
coalex/otel/safe_exporter.py
coalex/otel/span_processor.py
coalex-0.4.5.dist-info/licenses/LICENSE
coalex-0.4.5.dist-info/METADATA
coalex-0.4.5.dist-info/WHEEL
coalex-0.4.5.dist-info/top_level.txt
coalex-0.4.5.dist-info/RECORD
