Metadata-Version: 2.4
Name: coalex
Version: 0.4.5
Summary: OpenTelemetry SDK for Coalex.ai with OTLP integration
Author-email: "Coalex.ai" <support@coalex.ai>
License: MIT
Project-URL: Homepage, https://github.com/coalex-ai/coalex
Project-URL: Repository, https://github.com/coalex-ai/coalex
Project-URL: Issues, https://github.com/coalex-ai/coalex/issues
Classifier: Development Status :: 3 - Alpha
Classifier: Intended Audience :: Developers
Classifier: License :: OSI Approved :: MIT License
Classifier: Programming Language :: Python :: 3
Classifier: Programming Language :: Python :: 3.8
Classifier: Programming Language :: Python :: 3.9
Classifier: Programming Language :: Python :: 3.10
Classifier: Programming Language :: Python :: 3.11
Classifier: Programming Language :: Python :: 3.12
Requires-Python: >=3.8
License-File: LICENSE
Requires-Dist: opentelemetry-api>=1.20.0
Requires-Dist: opentelemetry-sdk>=1.20.0
Requires-Dist: opentelemetry-exporter-otlp>=1.20.0
Requires-Dist: opentelemetry-instrumentation>=0.41b0
Requires-Dist: requests>=2.28.0
Provides-Extra: dev
Requires-Dist: pytest>=7.0.0; extra == "dev"
Requires-Dist: pytest-cov>=4.0.0; extra == "dev"
Requires-Dist: black>=22.0.0; extra == "dev"
Requires-Dist: isort>=5.10.0; extra == "dev"
Requires-Dist: mypy>=1.0.0; extra == "dev"
Requires-Dist: grpcio-tools>=1.50.0; extra == "dev"
Provides-Extra: examples
Requires-Dist: openinference-instrumentation-vertexai; extra == "examples"
Requires-Dist: google-cloud-aiplatform; extra == "examples"
Dynamic: license-file
